wurst/__init__.py
wurst/errors.py
wurst/filesystem.py
wurst/geo.py
wurst/linking.py
wurst/logging_config.py
wurst/searching.py
wurst/IMAGE/__init__.py
wurst/IMAGE/calc_utils.py
wurst/IMAGE/electricity.py
wurst/IMAGE/io.py
wurst/IMAGE/metadata/region-topology.json
wurst/REMIND/__init__.py
wurst/REMIND/calc_utils.py
wurst/REMIND/electricity.py
wurst/REMIND/io.py
wurst/REMIND/metadata/region-topology.json
wurst/brightway/__init__.py
wurst/brightway/extract_database.py
wurst/brightway/write_database.py
wurst/brightway25/__init__.py
wurst/ecoinvent/__init__.py
wurst/ecoinvent/electricity_markets.py
wurst/ecoinvent/filters.py
wurst/transformations/__init__.py
wurst/transformations/activity.py
wurst/transformations/cleaning.py
wurst/transformations/geo.py
wurst/transformations/uncertainty.py
wurst/transformations/utils.py
wurst/transformations/markets/__init__.py
wurst/transformations/markets/markets.py
wurst/transformations/markets/utils.py
wurst-0.5.3.dist-info/licenses/LICENSE
wurst-0.5.3.dist-info/METADATA
wurst-0.5.3.dist-info/WHEEL
wurst-0.5.3.dist-info/top_level.txt
wurst-0.5.3.dist-info/RECORD
