Metadata-Version: 2.4
Name: wurst
Version: 0.5.3
Summary: Wurst is a python package for linking and modifying industrial ecology models
Author-email: Chris Mutel <cmutel@gmail.com>, Romain Sacchi <r_s@me.com>
Maintainer-email: Chris Mutel <cmutel@gmail.com>
Project-URL: source, https://github.com/polca/wurst
Project-URL: homepage, https://github.com/polca/wurst
Project-URL: tracker, https://github.com/polca/wurst/issues
Classifier: Development Status :: 4 - Beta
Classifier: Programming Language :: Python
Classifier: Programming Language :: Python :: 3
Classifier: Programming Language :: Python :: 3.10
Classifier: Programming Language :: Python :: 3.11
Classifier: Programming Language :: Python :: 3.12
Classifier: Programming Language :: Python :: 3.13
Classifier: Programming Language :: Python :: 3.14
Classifier: Natural Language :: English
Classifier: Operating System :: OS Independent
Classifier: Topic :: Scientific/Engineering
Requires-Python: >=3.9
License-File: LICENSE
Requires-Dist: platformdirs
Requires-Dist: constructive_geometries>=0.9.4
Requires-Dist: docopt
Requires-Dist: numpy
Requires-Dist: pandas
Requires-Dist: python-json-logger
Requires-Dist: structlog
Requires-Dist: toolz
Requires-Dist: tqdm
Requires-Dist: wrapt
Provides-Extra: testing
Requires-Dist: wurst; extra == "testing"
Requires-Dist: pytest; extra == "testing"
Requires-Dist: pytest-cov; extra == "testing"
Requires-Dist: pytest-randomly; extra == "testing"
Requires-Dist: python-coveralls; extra == "testing"
Provides-Extra: dev
Requires-Dist: build; extra == "dev"
Requires-Dist: pylint; extra == "dev"
Requires-Dist: pytest; extra == "dev"
Requires-Dist: pytest-cov; extra == "dev"
Requires-Dist: pytest-randomly; extra == "dev"
Requires-Dist: setuptools; extra == "dev"
Dynamic: license-file
